Metadata-Version: 2.1
Name: odoo13-addon-mrp-planned-order-matrix
Version: 13.0.1.0.1.dev12
Summary: Allows to create fixed planned orders on a grid view.
Home-page: https://github.com/OCA/manufacture
Author: ForgeFlow, Odoo Community Association (OCA)
Author-email: support@odoo-community.org
License: AGPL-3
Platform: UNKNOWN
Classifier: Programming Language :: Python
Classifier: Framework :: Odoo
Classifier: Framework :: Odoo :: 13.0
Classifier: License :: OSI Approved :: GNU Affero General Public License v3
Requires-Python: >=3.5
Requires-Dist: odoo13-addon-date-range
Requires-Dist: odoo13-addon-mrp-multi-level
Requires-Dist: odoo13-addon-web-widget-x2many-2d-matrix
Requires-Dist: odoo <13.1dev,>=13.0a
